<annotation verified="yes">
	<folder>images</folder>
	<filename>59925073_4d484c2b49.jpg</filename>
	<path>/home/usckiki/Documents/git/mask-query-aide/data/hardhat/train/images/59925073_4d484c2b49.jpg</path>
	<source>
		<database>Unknown</database>
	</source>
	<size>
		<width>499</width>
		<height>325</height>
		<depth>3</depth>
	</size>
	<segmented>0</segmented>
	<object>
		<name>person hardhat</name>
		<pose>Unspecified</pose>
		<truncated>0</truncated>
		<difficult>0</difficult>
		<bndbox>
			<xmin>148</xmin>
			<ymin>75</ymin>
			<xmax>321</xmax>
			<ymax>227</ymax>
		</bndbox>
	</object>
</annotation>
